README.md
setup.py
CSVLibrary/__init__.py
CSVLibrary/version.py
robotframework_csvlibrary_py3.egg-info/PKG-INFO
robotframework_csvlibrary_py3.egg-info/SOURCES.txt
robotframework_csvlibrary_py3.egg-info/dependency_links.txt
robotframework_csvlibrary_py3.egg-info/requires.txt
robotframework_csvlibrary_py3.egg-info/top_level.txt